{"cameraMode":{"drawMode":0,"name":"Shaded","section":"Shading Mode"},"sceneLighting":true,"audioPlay":false,"sceneViewState":{"m_AlwaysRefresh":false,"showFog":true,"showSkybox":true,"showFlares":true,"showImageEffects":true,"showParticleSystems":true,"showVisualEffectGraphs":true,"m_FxEnabled":true},"in2DMode":false,"pivot":{"x":5.212033271789551,"y":-7.141765594482422,"z":-25.265602111816408},"rotation":{"x":0.03588740527629852,"y":0.9610258340835571,"z":-0.22907669842243195,"w":0.15055562555789948},"size":54.2852783203125,"orthographic":false}