{"cameraMode":{"drawMode":0,"name":"Shaded","section":"Shading Mode"},"sceneLighting":true,"audioPlay":false,"sceneViewState":{"showFog":true,"showMaterialUpdate":false,"showSkybox":true,"showFlares":true,"showImageEffects":true,"showParticleSystems":true},"in2DMode":false,"pivot":{"x":-71.494384765625,"y":-40.81752014160156,"z":8.021415710449219},"rotation":{"x":0.25363314151763918,"y":-0.4010127782821655,"z":0.11657340824604035,"w":0.8725090026855469},"size":71.87500762939453,"orthographic":false}